obscene_words_filter
