Metadata-Version: 1.1
Name: python-obscene-words-filter
Version: 0.1.5
Summary: Obscene words filter for python, built on regexp for Russian language.
Home-page: https://github.com/asyncee/python-obscene-words-filter
Author: asyncee
Author-email: UNKNOWN
License: MIT
Download-URL: https://pypi.python.org/pypi/python-obscene-words-filter/
Keywords: obscene swear words filter
Platform: UNKNOWN
Classifier: Development Status :: 3 - Alpha
Classifier: Intended Audience :: Developers
Classifier: License :: OSI Approved :: MIT License
Classifier: Programming Language :: Python
Classifier: Programming Language :: Python :: 2
Classifier: Programming Language :: Python :: 2.7
Classifier: Topic :: Software Development :: Libraries :: Python Modules
